{"_ts":[1522572553],"_r":{"breakdown":{"html":{"bytes":[22421],"requests":[5]},"js":{"bytes":[551772],"requests":[44]},"css":{"bytes":[158847],"requests":[11]},"image":{"bytes":[677871],"requests":[32]},"flash":{"bytes":[0],"requests":[0]},"font":{"bytes":[337218],"requests":[8]},"video":{"bytes":[0],"requests":[0]},"other":{"bytes":[130],"requests":[1]}},"date":[1522572553],"domElements":[574],"domInteractive":[2249],"firstPaint":[1359.7000000009],"fullyLoaded":[4334],"id":["180401_D2_93f338513fbbee08e0a800f4b07ae6d3"],"loadTime":[3894],"render":[1500],"SpeedIndex":[1587],"TTFB":[207],"videoFrames":[[{"_i":"ms_000000.jpg","_t":0,"_vc":0},{"_i":"ms_001500.jpg","_t":1500,"_vc":81},{"_i":"ms_001600.jpg","_t":1600,"_vc":83},{"_i":"ms_001700.jpg","_t":1700,"_vc":84},{"_i":"ms_001800.jpg","_t":1800,"_vc":87},{"_i":"ms_001900.jpg","_t":1900,"_vc":98},{"_i":"ms_002100.jpg","_t":2100,"_vc":97},{"_i":"ms_002200.jpg","_t":2200,"_vc":98},{"_i":"ms_002300.jpg","_t":2300,"_vc":100},{"_i":"ms_002500.jpg","_t":2500,"_vc":98},{"_i":"ms_003100.jpg","_t":3100,"_vc":99},{"_i":"ms_003200.jpg","_t":3200,"_vc":100}]],"visualComplete":[2300],"lighthouse":[54],"pagespeed":[85]}}